carebt/__init__.py
carebt/abstractLogger.py
carebt/actionNode.py
carebt/behaviorTreeRunner.py
carebt/contingencyHistoryEntry.py
carebt/controlNode.py
carebt/executionContext.py
carebt/fallbackNode.py
carebt/nodeStatus.py
carebt/parallelNode.py
carebt/rateControlNode.py
carebt/rootNode.py
carebt/sequenceNode.py
carebt/simplePrintLogger.py
carebt/treeNode.py
carebt/examples/__init__.py
carebt/examples/action_with_params.py
carebt/examples/fallback.py
carebt/examples/helloworld.py
carebt/examples/longrun_actions.py
carebt/examples/parallel.py
carebt/examples/ratecontrol.py
carebt/examples/sequence_with_contingencies.py
carebt/examples/simple_sequence.py
carebt-1.2.2.dist-info/LICENSE
carebt-1.2.2.dist-info/METADATA
carebt-1.2.2.dist-info/WHEEL
carebt-1.2.2.dist-info/top_level.txt
carebt-1.2.2.dist-info/RECORD
