Metadata-Version: 2.1
Name: carebt
Version: 1.2.2
Summary: A Python library for contingency aware Behavior Trees (careBT)
Home-page: https://github.com/careBT/carebt_core
Author: Andreas Steck
Author-email: steck.andi@gmail.com
License: Apache License 2.0
Project-URL: Bug Tracker, https://github.com/careBT/carebt_core/issues
Platform: UNKNOWN
Classifier: Programming Language :: Python :: 3
Classifier: License :: OSI Approved :: Apache Software License
License-File: LICENSE
